{
  "db_name": "SQLite",
  "query": "SELECT EXISTS(\n                 SELECT 1 FROM routine_runs\n                 WHERE routine_id = $1 AND status IN ('pending','running')\n               ) AS \"exists!: bool\"",
  "describe": {
    "columns": [
      {
        "name": "exists!: bool",
        "ordinal": 0,
        "type_info": "Integer"
      }
    ],
    "parameters": {
      "Right": 1
    },
    "nullable": [
      false
    ]
  },
  "hash": "7cf5c0c3697dfd368d480449d198d50d580fa91d491ff3e0829febcaa91d4ae5"
}
